openaerostruct/__init__.py
openaerostruct/aerodynamics/__init__.py
openaerostruct/aerodynamics/aero_groups.py
openaerostruct/aerodynamics/coeffs.py
openaerostruct/aerodynamics/collocation_points.py
openaerostruct/aerodynamics/compressible_states.py
openaerostruct/aerodynamics/convert_velocity.py
openaerostruct/aerodynamics/eval_mtx.py
openaerostruct/aerodynamics/eval_velocities.py
openaerostruct/aerodynamics/functionals.py
openaerostruct/aerodynamics/geometry.py
openaerostruct/aerodynamics/get_vectors.py
openaerostruct/aerodynamics/horseshoe_circulations.py
openaerostruct/aerodynamics/lift_coeff_2D.py
openaerostruct/aerodynamics/lift_drag.py
openaerostruct/aerodynamics/mesh_point_forces.py
openaerostruct/aerodynamics/mtx_rhs.py
openaerostruct/aerodynamics/panel_forces.py
openaerostruct/aerodynamics/panel_forces_surf.py
openaerostruct/aerodynamics/pg_scale.py
openaerostruct/aerodynamics/pg_transform.py
openaerostruct/aerodynamics/pg_wind_rotation.py
openaerostruct/aerodynamics/rotational_velocity.py
openaerostruct/aerodynamics/solve_matrix.py
openaerostruct/aerodynamics/states.py
openaerostruct/aerodynamics/total_drag.py
openaerostruct/aerodynamics/total_lift.py
openaerostruct/aerodynamics/viscous_drag.py
openaerostruct/aerodynamics/vortex_mesh.py
openaerostruct/aerodynamics/wave_drag.py
openaerostruct/common/__init__.py
openaerostruct/common/atmos_comp.py
openaerostruct/common/atmos_group.py
openaerostruct/common/reynolds_comp.py
openaerostruct/docs/__init__.py
openaerostruct/docs/conf.py
openaerostruct/docs/wingbox_mpt_opt_example.py
openaerostruct/docs/_utils/__init__.py
openaerostruct/docs/_utils/generate_sourcedocs.py
openaerostruct/docs/_utils/patch.py
openaerostruct/functionals/__init__.py
openaerostruct/functionals/breguet_range.py
openaerostruct/functionals/center_of_gravity.py
openaerostruct/functionals/equilibrium.py
openaerostruct/functionals/moment_coefficient.py
openaerostruct/functionals/sum_areas.py
openaerostruct-2.12.0.dist-info/LICENSE.md
openaerostruct-2.12.0.dist-info/METADATA
openaerostruct-2.12.0.dist-info/WHEEL
openaerostruct-2.12.0.dist-info/entry_points.txt
openaerostruct-2.12.0.dist-info/top_level.txt
openaerostruct-2.12.0.dist-info/RECORD
