Metadata-Version: 2.1
Name: openaerostruct
Version: 2.12.0
Summary: OpenAeroStruct
Home-page: https://github.com/mdolab/OpenAeroStruct
Author: 
Author-email: 
License: BSD-3
Platform: UNKNOWN
Requires-Dist: openmdao!=3.40,>=3.35
Requires-Dist: numpy>=1.21
Requires-Dist: scipy>=1.7
Requires-Dist: matplotlib
Provides-Extra: all
Requires-Dist: mphys>=2.0.0; extra == "all"
Requires-Dist: pygeo>=1.15.0; extra == "all"
Requires-Dist: pygeo>=1.6.0; extra == "all"
Requires-Dist: sphinx-mdolab-theme; extra == "all"
Requires-Dist: testflo; extra == "all"
Provides-Extra: docs
Requires-Dist: sphinx-mdolab-theme; extra == "docs"
Provides-Extra: ffd
Requires-Dist: pygeo>=1.6.0; extra == "ffd"
Provides-Extra: mphys
Requires-Dist: mphys>=2.0.0; extra == "mphys"
Requires-Dist: pygeo>=1.15.0; extra == "mphys"
Provides-Extra: test
Requires-Dist: testflo; extra == "test"
